google_ldap3/__init__.py
google_ldap3/version.py
google_ldap3/abstract/__init__.py
google_ldap3/abstract/attrDef.py
google_ldap3/abstract/attribute.py
google_ldap3/abstract/cursor.py
google_ldap3/abstract/entry.py
google_ldap3/abstract/objectDef.py
google_ldap3/core/__init__.py
google_ldap3/core/connection.py
google_ldap3/core/exceptions.py
google_ldap3/core/pooling.py
google_ldap3/core/rdns.py
google_ldap3/core/results.py
google_ldap3/core/server.py
google_ldap3/core/timezone.py
google_ldap3/core/tls.py
google_ldap3/core/usage.py
google_ldap3/extend/__init__.py
google_ldap3/extend/operation.py
google_ldap3/extend/microsoft/__init__.py
google_ldap3/extend/microsoft/addMembersToGroups.py
google_ldap3/extend/microsoft/dirSync.py
google_ldap3/extend/microsoft/modifyPassword.py
google_ldap3/extend/microsoft/persistentSearch.py
google_ldap3/extend/microsoft/removeMembersFromGroups.py
google_ldap3/extend/microsoft/unlockAccount.py
google_ldap3/extend/novell/__init__.py
google_ldap3/extend/novell/addMembersToGroups.py
google_ldap3/extend/novell/checkGroupsMemberships.py
google_ldap3/extend/novell/endTransaction.py
google_ldap3/extend/novell/getBindDn.py
google_ldap3/extend/novell/listReplicas.py
google_ldap3/extend/novell/nmasGetUniversalPassword.py
google_ldap3/extend/novell/nmasSetUniversalPassword.py
google_ldap3/extend/novell/partition_entry_count.py
google_ldap3/extend/novell/removeMembersFromGroups.py
google_ldap3/extend/novell/replicaInfo.py
google_ldap3/extend/novell/startTransaction.py
google_ldap3/extend/standard/PagedSearch.py
google_ldap3/extend/standard/PersistentSearch.py
google_ldap3/extend/standard/__init__.py
google_ldap3/extend/standard/modifyPassword.py
google_ldap3/extend/standard/whoAmI.py
google_ldap3/operation/__init__.py
google_ldap3/operation/abandon.py
google_ldap3/operation/add.py
google_ldap3/operation/bind.py
google_ldap3/operation/compare.py
google_ldap3/operation/delete.py
google_ldap3/operation/extended.py
google_ldap3/operation/modify.py
google_ldap3-0.0.11.dist-info/LICENSE
google_ldap3-0.0.11.dist-info/METADATA
google_ldap3-0.0.11.dist-info/WHEEL
google_ldap3-0.0.11.dist-info/top_level.txt
google_ldap3-0.0.11.dist-info/RECORD
